ctakesclient/__init__.py
ctakesclient/client.py
ctakesclient/exceptions.py
ctakesclient/filesystem.py
ctakesclient/text2fhir.py
ctakesclient/transformer.py
ctakesclient/typesystem.py
ctakesclient/resources/SemGroups_2018.bsv
ctakesclient/resources/covid_symptoms.bsv
ctakesclient-5.1.0.dist-info/LICENSE
ctakesclient-5.1.0.dist-info/WHEEL
ctakesclient-5.1.0.dist-info/METADATA
ctakesclient-5.1.0.dist-info/RECORD
