Metadata-Version: 2.1
Name: ctakesclient
Version: 5.1.0
Summary: cTAKES client support for accessing cTAKES REST services
Author-email: "Andy McMurry, PhD" <andrew.mcmurry@childrens.harvard.edu>, Michael Terry <michael.terry@childrens.harvard.edu>, Tim Miller <timothy.miller@childrens.harvard.edu>
Requires-Python: >= 3.8
Classifier: License :: OSI Approved :: Apache Software License
Classifier: Operating System :: OS Independent
Classifier: Programming Language :: Python :: 3
Classifier: Topic :: Software Development :: Libraries :: Python Modules
Requires-Dist: fhirclient >= 4.1
Requires-Dist: httpx
Requires-Dist: pre-commit ; extra == "dev"
Requires-Dist: myst-parser ; extra == "docs"
Requires-Dist: sphinx < 6 ; extra == "docs"
Requires-Dist: sphinx-rtd-theme ; extra == "docs"
Requires-Dist: ddt ; extra == "tests"
Requires-Dist: pytest ; extra == "tests"
Requires-Dist: respx ; extra == "tests"
Project-URL: Homepage, https://github.com/Machine-Learning-for-Medical-Language/ctakes-client-py
Provides-Extra: dev
Provides-Extra: docs
Provides-Extra: tests
